feedparser_rs/__init__.py
feedparser_rs/_feedparser_rs.cpython-311-darwin.so
feedparser_rs/py.typed
feedparser_rs-0.4.3.dist-info/METADATA
feedparser_rs-0.4.3.dist-info/WHEEL
feedparser_rs-0.4.3.dist-info/RECORD
