Metadata-Version: 2.4
Name: feedparser-rs
Version: 0.4.3
Classifier: Development Status :: 4 - Beta
Classifier: Intended Audience :: Developers
Classifier: License :: OSI Approved :: MIT License
Classifier: License :: OSI Approved :: Apache Software License
Classifier: Programming Language :: Python :: 3
Classifier: Programming Language :: Python :: 3.10
Classifier: Programming Language :: Python :: 3.11
Classifier: Programming Language :: Python :: 3.12
Classifier: Programming Language :: Python :: 3.13
Classifier: Programming Language :: Rust
Classifier: Topic :: Text Processing :: Markup :: XML
Summary: High-performance RSS/Atom/JSON Feed parser with feedparser-compatible API
Keywords: rss,atom,feed,parser,feedparser,rust
License: MIT OR Apache-2.0
Requires-Python: >=3.10
Project-URL: Documentation, https://github.com/bug-ops/feedparser-rs#readme
Project-URL: Homepage, https://github.com/bug-ops/feedparser-rs
Project-URL: Repository, https://github.com/bug-ops/feedparser-rs
